Jquery180BangzhuWendang/README.md
Jquery180BangzhuWendang/__init__.py
Jquery180BangzhuWendang/__main__.py
Jquery180BangzhuWendang/file.epub
Jquery180BangzhuWendang/index.html
Jquery180BangzhuWendang/css/__init__.py
Jquery180BangzhuWendang/css/annotations.css
Jquery180BangzhuWendang/css/main.css
Jquery180BangzhuWendang/css/normalize.css
Jquery180BangzhuWendang/css/popup.css
Jquery180BangzhuWendang/font/__init__.py
Jquery180BangzhuWendang/font/fontello.eot
Jquery180BangzhuWendang/font/fontello.svg
Jquery180BangzhuWendang/font/fontello.ttf
Jquery180BangzhuWendang/font/fontello.woff
Jquery180BangzhuWendang/img/__init__.py
Jquery180BangzhuWendang/img/annotator-glyph-sprite.png
Jquery180BangzhuWendang/img/annotator-icon-sprite.png
Jquery180BangzhuWendang/img/apple-touch-icon.png
Jquery180BangzhuWendang/img/cancelfullscreen.png
Jquery180BangzhuWendang/img/close.png
Jquery180BangzhuWendang/img/fullscreen.png
Jquery180BangzhuWendang/img/loader.gif
Jquery180BangzhuWendang/img/menu-icon.png
Jquery180BangzhuWendang/img/save.png
Jquery180BangzhuWendang/img/saved.png
Jquery180BangzhuWendang/img/settings-s.png
Jquery180BangzhuWendang/img/settings.png
Jquery180BangzhuWendang/img/star.png
Jquery180BangzhuWendang/js/__init__.py
Jquery180BangzhuWendang/js/epub.js
Jquery180BangzhuWendang/js/epub.min.js
Jquery180BangzhuWendang/js/epub.min.map
Jquery180BangzhuWendang/js/hooks.min.js
Jquery180BangzhuWendang/js/hooks.min.map
Jquery180BangzhuWendang/js/reader.js
Jquery180BangzhuWendang/js/reader.js.map
Jquery180BangzhuWendang/js/reader.min.js
Jquery180BangzhuWendang/js/reader.min.map
Jquery180BangzhuWendang/js/hooks/__init__.py
Jquery180BangzhuWendang/js/hooks/extensions/__init__.py
Jquery180BangzhuWendang/js/hooks/extensions/highlight.js
Jquery180BangzhuWendang/js/libs/__init__.py
Jquery180BangzhuWendang/js/libs/jquery.min.js
Jquery180BangzhuWendang/js/libs/localforage.min.js
Jquery180BangzhuWendang/js/libs/screenfull.js
Jquery180BangzhuWendang/js/libs/screenfull.min.js
jquery1_8_0_bangzhu_wendang-2024.3.1.0.dist-info/METADATA
jquery1_8_0_bangzhu_wendang-2024.3.1.0.dist-info/WHEEL
jquery1_8_0_bangzhu_wendang-2024.3.1.0.dist-info/entry_points.txt
jquery1_8_0_bangzhu_wendang-2024.3.1.0.dist-info/top_level.txt
jquery1_8_0_bangzhu_wendang-2024.3.1.0.dist-info/RECORD
